Workbook
Name Slicer_Segment: #N/A

Sheet AMZN_Cash flow
A2: Particulars | B2: 2023 | C2: 2024 | D2: 2025
A3: CASH, CASH EQUIVALENTS, AND RESTRICTED CASH, BEGINNING OF PERIOD | B3: 54,253 | C3: 73,890 | D3: 82,312
A4: OPERATING ACTIVITIES:
A5: Net income | B5: 30,425 | C5: 59,248 | D5: 77,670
A6: Adjustments to reconcile net income to net cash from operating activities:
A7: Depreciation and amortization of property and equipment and capitalized content costs, operating lease assets, and other | B7: 48,663 | C7: 52,795 | D7: 65,756
A8: Stock-based compensation | B8: 24,023 | C8: 22,011 | D8: 19,467
A10: Non-operating expense (income), net | B10: -748 | C10: 2,012 | D10: -14880
A11: Deferred income taxes | B11: -5876 | C11: -4648 | D11: 11,470
A12: Changes in operating assets and liabilities:
A13: Inventories | B13: 1,449 | C13: -1884 | D13: -3002
A14: Accounts receivable, net and other | B14: -8348 | C14: -3249 | D14: -7333
A15: Other assets | B15: -12265 | C15: -14483 | D15: -15632
A16: Accounts payable | B16: 5,473 | C16: 2,972 | D16: 11,231
A17: Accrued expenses and other | B17: -2428 | C17: -2904 | D17: -5019
A18: Unearned revenue | B18: 4,578 | C18: 4,007 | D18: -214
A19: Net cash provided by (used in) operating activities | B19: 84946 | C19: 115877 | D19: 139514
A20: INVESTING ACTIVITIES:
A21: Purchases of property and equipment | B21: -52729 | C21: -82999 | D21: -131819
A22: Proceeds from property and equipment sales and incentives | B22: 4,596 | C22: 5,341 | D22: 3,499
A23: Acquisitions, net of cash acquired, non-marketable investments, and other, net | B23: -5839 | C23: -7082 | D23: -3841
A24: Sales and maturities of marketable securities | B24: 5,627 | C24: 16,403 | D24: 44,386
A25: Purchases of marketable securities | B25: -1488 | C25: -26005 | D25: -54770
A26: Net cash provided by (used in) investing activities | B26: -49833 | C26: -94342 | D26: -142545
A27: Free Cash Flow | B27: =B19+B21 -> 32217 | C27: =C19+C21 -> 32878 | D27: =D19+D21 -> 7695
A29: FINANCING ACTIVITIES:
A31: Proceeds from short-term debt, and other | B31: 18,129 | C31: 5,142 | D31: 9,320
A32: Repayments of short-term debt, and other | B32: -25677 | C32: -5060 | D32: -8426
A33: Proceeds from long-term debt | D33: 15,673
A34: Repayments of long-term debt | B34: -3676 | C34: -9182 | D34: -5021
A35: Principal repayments of finance leases | B35: -4384 | C35: -2043 | D35: -1557
A36: Principal repayments of financing obligations | B36: -271 | C36: -669 | D36: -328
A37: Net cash provided by (used in) financing activities | B37: -15879 | C37: -11812 | D37: 9,661
A38: Foreign currency effect on cash, cash equivalents, and restricted cash | B38: 403 | C38: -1301 | D38: 1,164
A39: Net increase (decrease) in cash, cash equivalents, and restricted cash | B39: 19,637 | C39: 8,422 | D39: 7,794
A40: CASH, CASH EQUIVALENTS, AND RESTRICTED CASH, END OF PERIOD | B40: 73,890 | C40: 82,312 | D40: 90,106
B42: $ in millions

Sheet AMZN_Income Statement
B2: 2023 | C2: 2024 | D2: 2025
A3: Net product sales | B3: 255887 | C3: 272311 | D3: 296266
A4: Net service sales | B4: 318898 | C4: 365648 | D4: 420658
A5: Total net sales | B5: 574785 | C5: 637959 | D5: 716924
A6: Operating expenses:
A7: Cost of sales | B7: 304739 | C7: 326288 | D7: 356414
A8: Gross profit | B8: =B5-B7 -> 270046 | C8: =C5-C7 -> 311671 | D8: =D5-D7 -> 360510
A10: Fulfillment | B10: 90619 | C10: 98505 | D10: 109074 | G10: =B8-(B15-B7) -> 36852
A11: Technology and infrastructure | B11: 85622 | C11: 88544 | D11: 108521
A12: Sales and marketing | B12: 44370 | C12: 43907 | D12: 47129
A13: General and administrative | B13: 11816 | C13: 11359 | D13: 11172
A14: Other operating expense (income), net | B14: 767 | C14: 763 | D14: 4639
A15: Total operating expenses | B15: 537933 | C15: 569366 | D15: 636949
A16: Operating income | B16: 36852 | C16: 68593 | D16: 79975
A17: Interest income | B17: 2949 | C17: 4677 | D17: 4381
A18: Interest expense | B18: -3182 | C18: -2406 | D18: -2274
A19: Other income (expense), net | B19: 938 | C19: -2250 | D19: 15229
A20: Total non-operating income | B20: 705 | C20: 21 | D20: 17336
A21: Income before income taxes | B21: 37557 | C21: 68614 | D21: 97311
A22: Provision for income taxes | B22: -7120 | C22: -9265 | D22: -19087
... A26: Diluted earnings per share | B26: 2.9 | C26: 5.53 | D26: 7.17
A27: Weighted-average shares used in computation of earnings per share:
A28: Basic | B28: 10304 | C28: 10473 | D28: 10656
A29: Diluted | B29: 10492 | C29: 10721 | D29: 10827

Sheet AMZN_Balance Sheet
B2: 2024 | C2: 2025
A3: Assets
A4: Current assets:
A5: Cash and cash equivalents | B5: 78779 | C5: 86810
A6: Marketable securities | B6: 22,423 | C6: 36,219
A7: Inventories | B7: 34214 | C7: 38325
A8: Accounts receivable, net and other | B8: 55,451 | C8: 67,729
A9: Total current assets | B9: 190867 | C9: 229083
A10: Property and equipment, net | B10: 252,665 | C10: 357,025
A11: Operating leases | B11: 76,141 | C11: 86,054
A12: Goodwill | B12: 23,074 | C12: 23,273
A13: Other assets | B13: 82,147 | C13: 122,607
A14: Total assets | B14: 624894 | C14: 818042
A16: LIABILITIES AND STOCKHOLDERS’ EQUITY
A17: Current liabilities:
A18: Accounts payable | B18: 94363 | C18: 121909
A19: Accrued expenses and other | B19: 66,965 | C19: 75,520
A20: Unearned revenue | B20: 18,103 | C20: 20,576
A21: Total current liabilities | B21: 179431 | C21: 218005
A22: Long-term lease liabilities | B22: 78277 | C22: 87339
A23: Long-term debt | B23: 52623 | C23: 65648
A24: Other long-term liabilities | B24: 28593 | C24: 35985
A25: Total Liabilities | B25: =SUM(B21:B24) -> 338924 | C25: =SUM(C21:C24) -> 406977
A27: Stockholders’ equity:
A28: Preferred stock ($0.01 par value; 500 shares authorized; no shares issued or outstanding) | B28: — | C28: —
A29: Common stock ($0.01 par value; 100,000 shares authorized; 11,108 and 11,246 shares issued; 10,593 and 10,731 shares outstanding) | B29: 111 | C29: 112
A30: Treasury stock, at cost | B30: -7837 | C30: -7837
A31: Additional paid-in capital | B31: 120,864 | C31: 140,024
A32: Accumulated other comprehensive income (loss) | B32: -34 | C32: 28,230
A33: Retained earnings | B33: 172,866 | C33: 250,536
A34: Total stockholders’ equity | B34: 285970 | C34: 411065
A35: Total liabilities and stockholders’ equity | B35: =B25+B34 -> 624894 | C35: =C25+C34 -> 818042
B37: $ in millions

Sheet 1) Financial_Analysis
A1: A. Revenue & Profit Trends
D2: 2024 | E2: 2025
A3: 1) YoY Revenue Growth rate: | D3: =('AMZN_Income Statement'!C5-'AMZN_Income Statement'!B5)/'AMZN_Income Statement'!B5 -> 0.10990892 | E3: =('AMZN_Income Statement'!D5-'AMZN_Income Statement'!C5)/'AMZN_Income Statement'!C5 -> 0.12377755
A4: 2) Revenue 2 year CAGR: | E4: =('AMZN_Income Statement'!D5/'AMZN_Income Statement'!B5)^0.5-1 -> 0.11682171
A5: 3) Net Income YoY growth rate: | D5: =('AMZN_Income Statement'!C24-'AMZN_Income Statement'!B24)/'AMZN_Income Statement'!B24 -> 0.94734593 | E5: =('AMZN_Income Statement'!D24-'AMZN_Income Statement'!C24)/'AMZN_Income Statement'!C24 -> 0.31093033
A7: B. Profit Margins (2023–2025)
C8: 2023 | D8: 2024 | E8: 2025
A9: 1) Gross profit Margin: | C9: ='AMZN_Income Statement'!B8/'AMZN_Income Statement'!B5 -> 0.46982089 | D9: ='AMZN_Income Statement'!C8/'AMZN_Income Statement'!C5 -> 0.48854393 | E9: ='AMZN_Income Statement'!D8/'AMZN_Income Statement'!D5 -> 0.50285665
A10: 2) Operating Profit Margin (EBIT Margin): | C10: ='AMZN_Income Statement'!B16/'AMZN_Income Statement'!B5 -> 0.064114408 | D10: ='AMZN_Income Statement'!C16/'AMZN_Income Statement'!C5 -> 0.10751945 | E10: ='AMZN_Income Statement'!D16/'AMZN_Income Statement'!D5 -> 0.11155297
A11: 3) Net Profit Margin: | C11: ='AMZN_Income Statement'!B24/'AMZN_Income Statement'!B5 -> 0.052932836 | D11: ='AMZN_Income Statement'!C24/'AMZN_Income Statement'!C5 -> 0.092871172 | E11: ='AMZN_Income Statement'!D24/'AMZN_Income Statement'!D5 -> 0.10833784
A13: C. Liquidity & Leverage Ratios (2024–2025)
C14: 2023 | D14: 2024 | E14: 2025
A15: 1) Current Ratio: | D15: ='AMZN_Balance Sheet'!B9/'AMZN_Balance Sheet'!B21 -> 1.0637348 | E15: ='AMZN_Balance Sheet'!C9/'AMZN_Balance Sheet'!C21 -> 1.0508153
A16: 2) Quick Ratio: | D16: =('AMZN_Balance Sheet'!B9-'AMZN_Balance Sheet'!B7)/'AMZN_Balance Sheet'!B21 -> 0.87305427 | E16: =('AMZN_Balance Sheet'!C9-'AMZN_Balance Sheet'!C7)/'AMZN_Balance Sheet'!C21 -> 0.87501663
A17: 3) Total Debt: | D17: ='AMZN_Balance Sheet'!B18+'AMZN_Balance Sheet'!B23 -> 146986 | E17: ='AMZN_Balance Sheet'!C18+'AMZN_Balance Sheet'!C23 -> 187557
A18: 4) Debt to Equity Ratio: | D18: ='1) Financial_Analysis'!D17/'AMZN_Balance Sheet'!B34 -> 0.51399098 | E18: ='1) Financial_Analysis'!E17/'AMZN_Balance Sheet'!C34 -> 0.45627091
A19: 5) Interest Coverage Ratio: | C19: ='AMZN_Income Statement'!B16/-('AMZN_Income Statement'!B18) -> 11.581395 | D19: ='AMZN_Income Statement'!C16/-('AMZN_Income Statement'!C18) -> 28.509144 | E19: ='AMZN_Income Statement'!D16/-('AMZN_Income Statement'!D18) -> 35.169305
A21: D. Cash Flow Analysis (2023–2025)
C22: 2023 | D22: 2024 | E22: 2025
A23: 1) Free cash flow margin: | C23: ='AMZN_Cash flow'!B27/'AMZN_Income Statement'!B5 -> 0.056050523 | D23: ='AMZN_Cash flow'!C27/'AMZN_Income Statement'!C5 -> 0.051536227 | E23: ='AMZN_Cash flow'!D27/'AMZN_Income Statement'!D5 -> 0.010733355
A24: 2) Free cash flow conersion: | C24: ='AMZN_Cash flow'!B27/'AMZN_Income Statement'!B24 -> 1.0588989 | D24: ='AMZN_Cash flow'!C27/'AMZN_Income Statement'!C24 -> 0.55492169 | E24: ='AMZN_Cash flow'!D27/'AMZN_Income Statement'!D24 -> 0.099073001

Sheet 2) Financial_Models
D2: 2024(Actual) | E2: 2025(Actual) | F2: 2026(Forecast) | G2: 2027(Forecast) | H2: 2028(Forecast) | O2: 2024 | P2: 2025 | Q2: 2026 | R2: 2027 | S2: 2028
A3: 1) Assumptions: | M3: Total revenue | O3: 637959 | P3: 716924 | Q3: 802954.88 | R3: 891279.92 | S3: 980407.91
B4: A) YoY Revenue Growth rate: | D4: ='1) Financial_Analysis'!D3 -> 0.10990892 | E4: ='1) Financial_Analysis'!E3 -> 0.12377755 | F4: =E4*(1+$J4) -> 0.12463586 | G4: =F4*(1+$J4) -> 0.12550012 | H4: =G4*(1+$J4) -> 0.12637038 | J4: =(E4-D4)/2 -> 0.0069343122 | M4: Operating profit margin | O4: =D14/D10 -> 0.10751945 | P4: =E14/E10 -> 0.11155297 | Q4: =F14/F10 -> 0.11334475 | R4: =G14/G10 -> 0.11513292 | S4: =H14/H10 -> 0.11691749
B5: B) COGS(As % of revenue): | D5: ='AMZN_Income Statement'!C7/'AMZN_Income Statement'!C5 -> 0.51145607 | E5: ='AMZN_Income Statement'!D7/'AMZN_Income Statement'!D5 -> 0.49714335 | F5: =E5*(1+$J5) -> 0.49358562 | G5: =F5*(1+$J5) -> 0.49005334 | H5: =G5*(1+$J5) -> 0.48654634 | J5: =(E5-D5)/2 -> -0.007156357
B6: C) Operating expenses(As % of revenue): | D6: ='AMZN_Income Statement'!C15/'AMZN_Income Statement'!C5 -> 0.89248055 | E6: ='AMZN_Income Statement'!D15/'AMZN_Income Statement'!D5 -> 0.88844703 | F6: =E6*(1+$J6) -> 0.88665525 | G6: =F6*(1+$J6) -> 0.88486708 | H6: =G6*(1+$J6) -> 0.88308251 | J6: =(E6-D6)/2 -> -0.0020167596 | P6: 2025 | Q6: 2026 | R6: 2027 | S6: 2028
B7: D) CapEx(As % of revenue): | D7: =-('AMZN_Cash flow'!C21)/'AMZN_Income Statement'!C5 -> 0.13010084 | E7: =-('AMZN_Cash flow'!D21)/'AMZN_Income Statement'!D5 -> 0.18386747 | F7: =E7*(1+$J7) -> 0.18881043 | G7: =F7*(1+$J7) -> 0.19388628 | H7: =G7*(1+$J7) -> 0.19909859 | J7: =(E7-D7)/2 -> 0.026883315 | M7: YoY EBIT Growth rate | P7: =(E14-D14)/D14 -> 0.1659353 | Q7: =(F14-E14)/E14 -> 0.14269996 | R7: =(G14-F14)/F14 -> 0.14325645 | S7: =(H14-G14)/G14 -> 0.14382916
M8: YoY Gross profit growth rate | P8: =(E12-D12)/D12 -> 0.1567005 | Q8: =(F12-E12)/E12 -> 0.13259271 | R8: =(G12-F12)/F12 -> 0.13335056 | S8: =(H12-G12)/G12 -> 0.13411664
A9: 2) Income statement projections: | M9: YoY COGS
B10: A) Total revenue: | D10: ='AMZN_Income Statement'!C5 -> 637959 | E10: ='AMZN_Income Statement'!D5 -> 716924 | F10: =E10*(1+F4) -> 806278.44 | G10: =F10*(1+G4) -> 907466.48 | H10: =G10*(1+H4) -> 1022143.4
B11: B) COGS: | D11: ='AMZN_Income Statement'!C7 -> 326288 | E11: ='AMZN_Income Statement'!D7 -> 356414 | F11: =F10*F5 -> 397967.44 | G11: =G10*G5 -> 444706.98 | H11: =H10*H5 -> 497320.12
B12: C) Gross Profit: | D12: =D10-D11 -> 311671 | E12: =E10-E11 -> 360510 | F12: =F10-F11 -> 408311 | G12: =G10-G11 -> 462759.5 | H12: =H10-H11 -> 524823.25
B13: D) Operating Expenses: | D13: =(D10*D6)-D11 -> 243078 | E13: =(E10*E6)-E11 -> 280535 | F13: =(F10*F6)-F11 -> 316923.57 | G13: =(G10*G6)-G11 -> 358280.23 | H13: =(H10*H6)-H11 -> 405316.81
B14: E) EBIT: | D14: =D12-D13 -> 68593 | E14: =E12-E13 -> 79975 | F14: =F12-F13 -> 91387.43 | G14: =G12-G13 -> 104479.27 | H14: =H12-H13 -> 119506.43
A16: 3) Cash flow projections: | D16: 2024 | E16: 2025 | F16: 2026 | G16: 2027 | H16: 2028
B17: A) Operating cash flow: | D17: ='AMZN_Cash flow'!C19 -> 115877 | E17: ='AMZN_Cash flow'!D19 -> 139514 | F17: =F14*(E17/E14) -> 159422.64 | G17: =G14*(F17/F14) -> 182260.96 | H17: =H14*(G17/G14) -> 208475.41
B18: B) CapEx: | D18: 82999 | E18: 131819 | F18: =F10*F7 -> 152233.78 | G18: =G10*G7 -> 175945.3 | H18: =H10*H7 -> 203507.3
B19: C) Free cash flow: | D19: =D17-D18 -> 32878 | E19: =E17-E18 -> 7695 | F19: =F17-F18 -> 7188.8609 | G19: =G17-G18 -> 6315.6598 | H19: =H17-H18 -> 4968.1019

Sheet 3) Valuation
D2: 2026 | E2: 2027 | F2: 2028
B3: 1) Projected Free Cash Flows: | D3: ='2) Financial_Models'!F19 -> 7188.8609 | E3: ='2) Financial_Models'!G19 -> 6315.6598 | F3: ='2) Financial_Models'!H19 -> 4968.1019
B4: 2) Discount Period(t): | D4: 1 | E4: 2 | F4: 3
B5: 3) Discount factor: | D5: =(1/(1+9%)^1) -> 0.91743119 | E5: =(1/(1+9%)^2) -> 0.84167999 | F5: =(1/(1+9%)^3) -> 0.77218348
B6: 4) Present Value of FCF: | D6: =D3*D5 -> 6595.2852 | E6: =E3*E5 -> 5315.7645 | F6: =F3*F5 -> 3836.2862 | G6: =SUM(D6:F6) -> 15747.336
B8: Terminal Value: | F8: =(G6*(1+3%))/(9%-3%) -> 270329.27
B9: PV of Terminal Value: | F9: =F8/(1+9%)^3 -> 208743.79
B10: Implied Enterprise value: | F10: =G6+F9 -> 224491.13
B11: Implied Equity value: | F11: =F10+'AMZN_Balance Sheet'!C5+'AMZN_Balance Sheet'!C18-'AMZN_Balance Sheet'!C23 -> 367562.13
B12: Target Share Price: | F12: =F11/1080 -> 340.33531

Sheet Financial_Dashboard

Sheet 4) Dashboard_Data
B2: Segment | E2: 2023 | F2: 2024 | G2: 2025 | H2: YoY Growth | I2: % of Total Revenue | R2: Row Labels | S2: Sum of 2025
B3: Online stores: | E3: 231872 | F3: 247029 | G3: 269287 | H3: =(G3-F3)/F3 -> 0.090102781 | I3: =G3/$G$10 -> 0.37561443 | R3: Advertising services: | S3: 68635
B4: Physical stores: | E4: 20030 | F4: 21215 | G4: 22561 | H4: =(G4-F4)/F4 -> 0.063445675 | I4: =G4/$G$10 -> 0.031469165 | R4: AWS(Amazon Web Services): | S4: 128725
B5: Third-party seller services: | E5: 140053 | F5: 156146 | G5: 172162 | H5: =(G5-F5)/F5 -> 0.10257067 | I5: =G5/$G$10 -> 0.24013982 | R5: Online stores: | S5: 269287
B6: Advertising services: | E6: 46906 | F6: 56214 | G6: 68635 | H6: =(G6-F6)/F6 -> 0.22095919 | I6: =G6/$G$10 -> 0.095735392 | R6: Physical stores: | S6: 22561
B7: Subscription services: | E7: 40209 | F7: 44374 | G7: 49619 | H7: =(G7-F7)/F7 -> 0.11819985 | I7: =G7/$G$10 -> 0.069210962 | R7: Subscription services: | S7: 49619
B8: AWS(Amazon Web Services): | E8: 90757 | F8: 107556 | G8: 128725 | H8: =(G8-F8)/F8 -> 0.1968184 | I8: =G8/$G$10 -> 0.17955181 | R8: Third-party seller services: | S8: 172162
B9: Other: | E9: 4958 | F9: 5425 | G9: 5935 | H9: =(G9-F9)/F9 -> 0.094009217 | I9: =G9/$G$10 -> 0.0082784228 | R9: Grand Total | S9: 710989
B10: Total Revenue | E10: =SUM(E3:E9) -> 574785 | F10: =SUM(F3:F9) -> 637959 | G10: =SUM(G3:G9) -> 716924 | H10: =(G10-F10)/F10 -> 0.12377755 | I10: =G10/$G$10 -> 1
B13: North America: | E13: 2023 | F13: 2024 | G13: 2025 | H13: YoY Growth | I13: % of Total Revenue
B14: Revenue | E14: 352828 | F14: 387497 | G14: 426305 | H14: 0.10015045 | I14: 0.59463067 | R14: Row Labels | S14: FY2023 | T14: FY2024 | U14: FY2025
B15: Operating Expense | E15: 337951 | F15: 362530 | G15: 396686 | H15: 0.094215651 | I15: 0.62279084 | R15: Advertising services: | S15: 46906 | T15: 56214 | U15: 68635
B16: Operating Income | E16: 14877 | F16: 24967 | G16: 29619 | H16: 0.18632595 | R16: AWS(Amazon Web Services): | S16: 90757 | T16: 107556 | U16: 128725
R17: Online stores: | S17: 231872 | T17: 247029 | U17: 269287
B18: International | E18: 2023 | F18: 2024 | G18: 2025 | H18: 0.00049407115 | R18: Physical stores: | S18: 20030 | T18: 21215 | U18: 22561
B19: Revenue | E19: 131200 | F19: 142906 | G19: 161894 | H19: 0.13287056 | I19: 0.22581752 | R19: Subscription services: | S19: 40209 | T19: 44374 | U19: 49619
B20: Operating Expense | E20: 133856 | F20: 139114 | G20: 157144 | H20: 0.12960593 | I20: 0.24671363 | R20: Third-party seller services: | S20: 140053 | T20: 156146 | U20: 172162
B21: Operating Income | E21: -2656 | F21: 3792 | G21: 4750 | H21: 0.25263713 | R21: Grand Total | S21: 569827 | T21: 632534 | U21: 710989
B23: AWS | E23: 2023 | F23: 2024 | G23: 2025 | H23: 0.00049407115
B24: Revenue | E24: 90757 | F24: 107556 | G24: 128725 | H24: 0.1968184 | I24: 0.17955181
B25: Operating Expense | E25: 66126 | F25: 67722 | G25: 83119 | H25: 0.22735596 | I25: 0.13049553 | R25: Row Labels | S25: Sum of YoY Growth
B26: Operating Income | E26: 24631 | F26: 39834 | G26: 45606 | H26: 0.14490134 | R26: Online stores: | S26: 0.090102781
R27: Physical stores: | S27: 0.063445675
R28: Third-party seller services: | S28: 0.10257067
E29: 2023 | F29: 2024 | G29: 2025 | H29: YoY Growth | I29: % of Total Revenue | R29: Subscription services: | S29: 0.11819985
B30: North America | E30: 352828 | F30: 387497 | G30: 426305 | H30: 0.10015045 | I30: 0.59463067 | R30: AWS(Amazon Web Services): | S30: 0.1968184
B31: International | E31: 131200 | F31: 142906 | G31: 161894 | H31: 0.13287056 | I31: 0.22581752 | R31: Advertising services: | S31: 0.22095919
B32: AWS | E32: 90757 | F32: 107556 | G32: 128725 | H32: 0.1968184 | I32: 0.17955181 | R32: Grand Total | S32: 0.79209657
S36: Column Labels
R37: Values | S37: Revenue | T37: Grand Total
R38: FY2023 | S38: 352828 | T38: 352828
R39: FY2024 | S39: 387497 | T39: 387497
R40: FY2025 | S40: 426305 | T40: 426305

Sheet 5) Dashboard

Sheet 6) Budget Vs Actual
D2: Revenue(2025 in millions) | E2: Operating Income(2025 in millions)
B3: Guidance Target | D3: 710000 | E3: 76000
B4: Actual Reported | D4: 716924 | E4: 79975
B5: Dollar Variance | D5: =D4-D3 -> 6924 | E5: =E4-E3 -> 3975
B6: % variance | D6: =D5/D3 -> 0.0097521127 | E6: =E5/E3 -> 0.052302632
D8: Favourable outcome | E8: Favourable outcome
